{
  "menu_dashboard_label": "Dashboard",
  "menu_dashboard_aria": "Ir al panel principal",
  "menu_productos_label": "Productos",
  "menu_productos_aria": "Ir a productos",
  "menu_usuarios_label": "Usuarios",
  "menu_usuarios_aria": "Ir a usuarios",
  "menu_reportes_label": "Reportes",
  "menu_reportes_aria": "Ir a reportes",
  "menu_ventas_label": "Ventas",
  "menu_ventas_aria": "Ir a ventas",
  "menu_rutas_label": "Rutas",
  "menu_rutas_aria": "Ir a rutas",
  "menu_settings_label": "Ajustes Regionales",
  "menu_settings_aria": "Ir a Ajustes Regionales",
  "app_logo_label": "Logo de la aplicación",
  "languageLabel": "Idioma",
  "countryLabel": "País",
  "saveButton": "Guardar",
  "language_es_co": "Español (Colombia)",
  "language_en_us": "Inglés (Estados Unidos)",
  "country_co": "Colombia",
  "country_pe": "Perú",
  "country_ec": "Ecuador",
  "country_mx": "México",
  "topbarLabel": "Encabezado de la página",
  "userBlockLabel": "Información del usuario",
  "regionSettingsLabel": "Ajustes regionales",
  "regionSettingsAlt": "Ajustes regionales",
  "userButtonLabel": "Perfil de usuario",
  "userDetailsLabel": "Detalles del usuario",
  "userNameLabel": "Nombre del usuario",
  "userGreeting": "Hola,",
  "userRoleLabel": "Rol del usuario",
  "userMenuLabel": "Menú de usuario",
  "logoutLabel": "Cerrar sesión",
  "logoutText": "Cerrar sesión",
  "pageDashboardTitle": "Dashboard",
  "pageRegionTitle": "Ajustes Regionales",
  "cardProductsTitle": "Carga de productos",
  "cardProductsSubtitle": "Subir plantilla",
  "cardProductsAria": "Card de carga de productos",
  "cardRoutesTitle": "Generar rutas",
  "cardRoutesSubtitle": "Generar ahora",
  "cardRoutesAria": "Card de rutas",
  "cardSalesTitle": "Crear plan de venta",
  "cardSalesSubtitle": "Crear ahora",
  "cardSalesAria": "Card de ventas",
  "cardUsersTitle": "Registro de usuarios",
  "cardUsersSubtitle": "Importar CSV",
  "cardUsersAria": "Card de usuarios",
  "cardReportsTitle": "Reportes",
  "cardReportsSubtitle": "Listar y generar métricas",
  "cardReportsAria": "Card de reportes"
}
